ansible_collections/python/dist/plugins/modules/boo.py
ansible_collections.python.dist.boo-0.1.2.dist-info/LICENSE
ansible_collections.python.dist.boo-0.1.2.dist-info/METADATA
ansible_collections.python.dist.boo-0.1.2.dist-info/WHEEL
ansible_collections.python.dist.boo-0.1.2.dist-info/top_level.txt
ansible_collections.python.dist.boo-0.1.2.dist-info/zip-safe
ansible_collections.python.dist.boo-0.1.2.dist-info/RECORD
