Metadata-Version: 2.1
Name: ansible-collections.python.dist.boo
Version: 0.1.2
Summary: Example Ansible Collection containing 'boo' Ansible module
Home-page: https://github.com/webknjaz/ansible-collection-python-dist-boo
Author: Sviatoslav Sydorenko (@webknjaz)
Author-email: wk+github/ansible@sydorenko.org.ua
License: GPLv3+
Project-URL: Bug Tracker, https://github.com/webknjaz/ansible-collection-python-dist-boo/issues
Project-URL: CI: GitHub, https://github.com/webknjaz/ansible-collection-python-dist-boo/actions
Project-URL: Source Code, https://github.com/webknjaz/ansible-collection-python-dist-boo
Keywords: Ansible,Ansible Collections,Ansible Module
Platform: UNKNOWN
Classifier: Development Status :: 2 - Pre-Alpha
Classifier: Environment :: Console
Classifier: Environment :: Other Environment
Classifier: Intended Audience :: Developers
Classifier: Intended Audience :: Information Technology
Classifier: Intended Audience :: System Administrators
Classifier: License :: OSI Approved :: GNU General Public License v3 or later (GPLv3+)
Classifier: Operating System :: OS Independent
Classifier: Operating System :: POSIX
Classifier: Programming Language :: Python
Classifier: Programming Language :: Python :: 3
Classifier: Programming Language :: Python :: 3.7
Classifier: Programming Language :: Python :: 3.8
Classifier: Programming Language :: Python :: Implementation
Classifier: Programming Language :: Python :: Implementation :: CPython
Classifier: Programming Language :: Python :: Implementation :: PyPy
Classifier: Topic :: Software Development
Classifier: Topic :: Software Development :: Libraries
Classifier: Topic :: Software Development :: Libraries :: Python Modules
Classifier: Topic :: Software Development :: Version Control
Classifier: Topic :: Software Development :: Version Control :: Git
Classifier: Topic :: System :: Networking
Classifier: Topic :: Utilities
Requires-Python: >=3.7
Requires-Dist: ansible
Requires-Dist: six
